isitgr/HighLExtrapTemplate_lenspotentialCls.dat
isitgr/PArthENoPE_880.2_marcucci.dat
isitgr/PArthENoPE_880.2_standard.dat
isitgr/PRIMAT_Yp_DH_Error.dat
isitgr/__init__.py
isitgr/_command_line.py
isitgr/_compilers.py
isitgr/_config.py
isitgr/baseconfig.py
isitgr/bbn.py
isitgr/bispectrum.py
isitgr/constants.py
isitgr/correlations.py
isitgr/dark_energy.py
isitgr/emission_angle.py
isitgr/initialpower.py
isitgr/isitgr.py
isitgr/isitgrlib.so
isitgr/mathutils.py
isitgr/model.py
isitgr/nonlinear.py
isitgr/postborn.py
isitgr/recombination.py
isitgr/reionization.py
isitgr/results.py
isitgr/sources.py
isitgr/symbolic.py
isitgr/tests/__init__.py
isitgr-1.0.3.dist-info/LICENCE.txt
isitgr-1.0.3.dist-info/METADATA
isitgr-1.0.3.dist-info/WHEEL
isitgr-1.0.3.dist-info/entry_points.txt
isitgr-1.0.3.dist-info/top_level.txt
isitgr-1.0.3.dist-info/RECORD
