Metadata-Version: 2.1
Name: isitgr
Version: 1.0.3
Summary: Integrated Software in Testing General Relativity (ISiTGR). Patch for the software CAMB
Home-page: https://github.com/mishakb/ISiTGR
Author: ISiTGR authors:Cristhian Garcia-Quintero, Mustapha Ishak. CAMB authors: Antony Lewis
Project-URL: Documentation, https://isitgr.readthedocs.org
Project-URL: Source, https://github.com/mishakb/ISiTGR
Project-URL: Reference, https://arxiv.org/abs/1908.00290
Project-URL: Licensing, https://github.com/cmbant/CAMB/blob/master/LICENCE.txt
Keywords: cosmology,CAMB,CMB,ISiTGR,Modified,Gravity
Platform: any
Classifier: Development Status :: 5 - Production/Stable
Classifier: Operating System :: OS Independent
Classifier: Intended Audience :: Science/Research
Classifier: Topic :: Scientific/Engineering :: Astronomy
Classifier: Programming Language :: Python :: 2
Classifier: Programming Language :: Python :: 2.7
Classifier: Programming Language :: Python :: 3
Classifier: Programming Language :: Python :: 3.6
Classifier: Programming Language :: Python :: 3.7
Classifier: Programming Language :: Python :: 3.8
Requires-Python: >=2.7,!=3.0.*,!=3.1.*,!=3.2.*,!=3.3.*,!=3.4.*,!=3.5.*
License-File: LICENCE.txt
Requires-Dist: scipy >=1.0
Requires-Dist: six
Requires-Dist: sympy >=1.0
